<?xml version="1.0" encoding="UTF-8"?>

<!--
	Upgrading Parts
-->

<string_table>

<!-- Outfits -->
	<string id="st_upgr_o_health">
		<text>生命维持系统原型</text>
	</string>
	<string id="st_upgr_o_health_desc">
		<text>这个套件中包含一个集成系统, 可以监控穿戴者的健康状况,并根据需要提供维生素, 肾上腺素或合成代谢物质.\n \n
		</text>
	</string>
	
	<string id="st_upgr_o_bleed">
		<text>疗伤系统原型</text>
	</string>
	<string id="st_upgr_o_bleed_desc">
		<text>这个套件中包含了用于及时进行连续给药的医疗设备.\n \n
		</text>
	</string>
	
	<string id="st_upgr_o_armor">
		<text>防弹套件</text>
	</string>
	<string id="st_upgr_o_armor_desc">
		<text>这个套件中包含各种类型的凯夫拉尔纤维, 钛, 绿柱石, 铝和碳纤维板, 以高贴合度和子弹防护作用为特点.\n \n</text>
	</string>
	
	<string id="st_upgr_o_damage">
		<text>装甲补偿层</text>
	</string>
	<string id="st_upgr_o_damage_desc">
		<text>该套件包含不同材料的特制装甲板, 可略微提高防弹能力.\n \n</text>
	</string>
	
	<string id="st_upgr_o_durability">
		<text>耐久板材及面料</text>
	</string>
	<string id="st_upgr_o_durability_desc">
		<text>该套件包含用于重型设备的钛和铝合金耐用装甲板, 以及用于较轻装备的聚合物嵌件.\n \n</text>
	</string>
	
	<string id="st_upgr_o_power">
		<text>塑料和合成零件</text>
	</string>
	<string id="st_upgr_o_power_desc">
		<text>该套件包含各种装甲服的合成材料和塑料部件, 用来减轻装甲的重量并增加机动性和耐力.\n \n</text>
	</string>
	
	<string id="st_upgr_o_chem">
		<text>化学阻燃剂和嵌件</text>
	</string>
	<string id="st_upgr_o_chem_desc">
		<text>该套件中包含一组有害的面料和材料, 可提高护甲防护性能, 防止化学影响,它们可以中断燃烧气相中的化学反应, 某些材料则会在保护层后膨胀的化学物质, 从而提供更多的隔离性\n \n</text>
	</string>
	
	<string id="st_upgr_o_burn">
		<text>阻燃面料和嵌件</text>
	</string>
	<string id="st_upgr_o_burn_desc">
		<text>该套件中包含一组性质不稳定的防护面料和材料, 可减慢或阻止火蔓延或降低火的强度. 有些是耐火材料, 含有不同长度, 宽度, 厚度和形状的镁.\n \n</text>
	</string>
	
	<string id="st_upgr_o_shock">
		<text>绝缘纺织品和嵌件</text>
	</string>
	<string id="st_upgr_o_shock_desc">
		<text>该套件包含一组保护性的康铜, 镁和硅胶嵌件, 用来减少电流对护甲的影响.\n \n</text>
	</string>
	
	<string id="st_upgr_o_psi">
		<text>面料保护涂层</text>
	</string>
	<string id="st_upgr_o_psi_desc">
		<text>该套件包含一组用于头盔和装甲服的屏蔽衬套和渗铝层, 并带有防脑波橡胶以减少psy辐射的影响.\n \n</text>
	</string>
	
	<string id="st_upgr_o_rad">
		<text>活性过滤器和辐射屏蔽材料</text>
	</string>
	<string id="st_upgr_o_rad_desc">
		<text>一套保护性过滤器, 防止各种毒性物质或化学物质通过呼吸系统进入人体, 其次是高密度材料, 降低阿尔法射线和伽马射线的侵害.\n \n</text>
	</string>
	
	<string id="st_upgr_o_carry">
		<text>负载分配紧固系统</text>
	</string>
	<string id="st_upgr_o_carry_desc">
		<text>该套件包含一组用于分配负载的各种紧固件.\n \n</text>
	</string>
	
	<string id="st_upgr_o_arty">
		<text>附件插槽</text>
	</string>
	<string id="st_upgr_o_arty_desc">
		<text>该套件包含附件插槽, 增加同时使用的装备和神器的数量.\n \n</text>
	</string>
	
	<string id="st_upgr_o_run">
		<text>伺服驱动液压助推传动装置</text>
	</string>
	<string id="st_upgr_o_run_desc">
		<text>该套件包含用于第一代和第二代外骨骼的增强型原型伺服驱动器,允许装备者进行疾跑.\n \n</text>
	</string>
	
	<string id="st_upgr_o_weight">
		<text>轻质材料</text>
	</string>
	<string id="st_upgr_o_weight_desc">
		<text>该套件包含一套不同长度, 宽度, 厚度和形状以及不同特性的轻质聚合物材料.\n \n</text>
	</string>

<!-- Weapons -->
	<string id="st_upgr_w_weight">
		<text>移动配重组件</text>
	</string>
	<string id="st_upgr_w_weight_desc">
		<text>该套件包含一套用于各种武器的轻质聚合物部件, 聚合物组件是相当受欢迎的升级方式, 拥有不错的成效.\n \n</text>
	</string>
	
	<string id="st_upgr_w_muffle">
		<text>枪管消音器螺纹套件</text>
	</string>
	<string id="st_upgr_w_muffle_desc">
		<text>该套件包含一组用于各种类型武器的外螺纹组件, 使得武器可以适配消音器.\n \n</text>
	</string>
	
	<string id="st_upgr_w_grenade_mount">
		<text>下挂榴弹发射器支架</text>
	</string>
	<string id="st_upgr_w_grenade_mount_desc">
		<text>该套件包含一套用于各种武器装备下挂榴弹发射器的支架.\n \n</text>
	</string>
	
	<string id="st_upgr_w_reliability">
		<text>自动节气阀</text>
	</string>
	<string id="st_upgr_w_reliability_desc">
		<text>该套件包含一套用于各种类型武器的特殊调节构造, 保护武器免受尘土侵害.\n \n</text>
	</string>
	
	<string id="st_upgr_w_speed">
		<text>附加膛线枪管</text>
	</string>
	<string id="st_upgr_w_speed_desc">
		<text>包含一组用于各种类型武器的附加膛线管. 安装带有附加膛线的枪管可提高子弹初度和武器精度, 但会增加后坐力.\n \n</text>
	</string>
	
	<string id="st_upgr_w_recoil">
		<text>附加导气活塞集</text>
	</string>
	<string id="st_upgr_w_recoil_desc">
		<text>该套件包含一组用于各种类型武器的附加导气活塞, 第二个活塞可使运动平衡, 以补偿螺栓机构的移动冲击.\n \n</text>
	</string>
	
	<string id="st_upgr_w_magazine">
		<text>大容量弹匣组</text>
	</string>
	<string id="st_upgr_w_magazine_desc">
		<text>该套件包含一组可用于各种武器的弹匣, 具有更大的容量.\n \n</text>
	</string>
	
	<string id="st_upgr_w_scope">
		<text>光学瞄准镜组件集</text>
	</string>
	<string id="st_upgr_w_scope_desc">
		<text>该套件包含一组用于各种类型武器的光学瞄准镜. 可满足近距离, 中距离和远距离作战的需要.\n \n</text>
	</string>
	
	<string id="st_upgr_w_dispersion">
		<text>平衡组件集</text>
	</string>
	<string id="st_upgr_w_dispersion_desc">
		<text>该软件包包含一组用于各种类型武器的平衡组件. 安装在杆上的合成组件可以确保组件严格按照路径移动, 从而提高了精度.\n \n</text>
	</string>
	
	<string id="st_upgr_w_calibre">
		<text>口径组件集</text>
	</string>
	<string id="st_upgr_w_calibre_desc">
		<text>该套件包含一套用于各种类型武器的口径部件, 对武器的机械和自动化部分进行复杂而且综合的改造, 这样就可以允许您在降低可靠性的同时改变它的口径\n \n</text>
	</string>
	
	<string id="st_upgr_w_inertion">
		<text>不同形状的人体工程学枪机</text>
	</string>
	<string id="st_upgr_w_inertion_desc">
		<text>包含一套用于各种类型武器的人体工程学枪机. 更符合人体工程学的枪机外形, 它能提高使用者一边移动一边射击时的手感.\n \n</text>
	</string>
	
	<string id="st_upgr_w_rpm">
		<text>钛合金击针装置</text>
	</string>
	<string id="st_upgr_w_rpm_desc">
		<text>该套件包含一套用于各种武器的钛棒, 钛棒比普通棒可承受更高的射速.\n \n</text>
	</string>
	
	<string id="st_upgr_w_scope_mount">
		<text>光学安装座集</text>
	</string>
	<string id="st_upgr_w_scope_mount_desc">
		<text>该套件包含一套用于各种类型武器的光学瞄准镜底座, 可使得武器安装光学瞄具.\n \n</text>
	</string>
	
	<string id="st_upgr_w_firemode">
		<text>扳机套件集</text>
	</string>
	<string id="st_upgr_w_firemode_desc">
		<text>包含一套用于各种类型武器的扳机系统, 使得武器适配自动模式.\n \n</text>
	</string>

</string_table>
